directory_validators/__init__.py
directory_validators/file.py
directory_validators/helper.py
directory_validators/password.py
directory_validators/string.py
directory_validators/url.py
directory_validators-9.4.0.dist-info/licenses/LICENSE
directory_validators-9.4.0.dist-info/METADATA
directory_validators-9.4.0.dist-info/WHEEL
directory_validators-9.4.0.dist-info/top_level.txt
directory_validators-9.4.0.dist-info/RECORD
